pyworks/__init__.py
pyworks/cli.py
pyworks/core.py
pyworks/logger.py
pyworks/net.py
pyworks/timer.py
pyworks/util.py
pyworks-0.9.1.dist-info/DESCRIPTION.rst
pyworks-0.9.1.dist-info/METADATA
pyworks-0.9.1.dist-info/RECORD
pyworks-0.9.1.dist-info/WHEEL
pyworks-0.9.1.dist-info/entry_points.txt
pyworks-0.9.1.dist-info/metadata.json
pyworks-0.9.1.dist-info/top_level.txt
