Metadata-Version: 2.0
Name: pyworks
Version: 0.9.1
Summary: An Task framework
Home-page: https://github.com/pylots/pyworks
Author: Rene Nejsum, __PYLOTS__
Author-email: rene@pylots.com
License: UNKNOWN
Project-URL: Bug Reports, https://github.com/pylots/pyworks/issues
Project-URL: Source, https://github.com/pylots/pyworks/
Keywords: actors concurrency development
Platform: UNKNOWN
Classifier: Development Status :: 3 - Alpha
Classifier: Intended Audience :: Developers
Classifier: Topic :: Software Development
Classifier: License :: OSI Approved :: MIT License
Classifier: Programming Language :: Python :: 3.6
Requires-Dist: jinja2
